quartus_proj_max10/hdl/DAC_SPI/DAC_SPI.vhdl
library ieee;
use ieee.std_logic_1164.all;
use ieee.numeric_std.all;


-- interfacing DAC chip via SPI, receiving data from Avalon-ST sink interface
entity DAC_SPI is
    port (
        clk     : in  std_logic;
        clk_spi : in  std_logic;
        rst     : in  std_logic;

        -- SPI output to DAC
        spi_clk  : out std_logic;
        spi_cs_n : out std_logic := '1';  -- active low chip select
        spi_data : out std_logic;

        -- Avalon-ST sink (16-bit)
        asi_data  : in  std_logic_vector(15 downto 0);
        asi_valid : in  std_logic;
        asi_ready : out std_logic
    );
end entity DAC_SPI;

architecture rtl of DAC_SPI is

    --Bit 3 and 2: which DAC (00 -> DAC0); Bit 1 and 0: Mode of Operation: 01 -> Write to reg and update output )
    constant preamble : std_logic_vector(3 downto 0) := "0001";  
    -- SPI clock domain
    signal shift_reg : std_logic_vector(15 downto 0);
    signal data_buffer : std_logic_vector(15 downto 0);
    signal bit_cnt   : unsigned(4 downto 0);
    signal s_reset : std_logic := '0';

    signal spi_transmission_done : std_logic := '0';
    signal transmission_in_progress_ff : std_logic_vector(1 downto 0) := (others => '0');
    signal transmission_in_progress : std_logic := '0';
    signal spi_busy : std_logic := '0';
    signal spi_transmission_start : std_logic := '0';

begin
    s_reset <= rst;


    p_asi_data_capture: process(all) is
    begin
        if s_reset = '1' then
            data_buffer <= (others => '0');
            asi_ready <= '1';
            transmission_in_progress <= '0';
        elsif rising_edge(clk) then
            if asi_valid = '1' and asi_ready = '1' then
                data_buffer <= asi_data;
                asi_ready <= '0';  -- not ready to accept new data until current is sent
                transmission_in_progress <= '1';
            elsif transmission_in_progress = '1' and spi_transmission_done = '1' then
                asi_ready <= '1';  -- ready for next data after transmission is done
                transmission_in_progress <= '0';
            end if;
        end if;
    end process;

    -- clock_crossing 200MHz --> 40 MHz
    p_clk_crossing: process(all) is
    begin
        if s_reset = '1' then
            transmission_in_progress_ff <= (others => '0');
        elsif rising_edge(clk_spi) then
            transmission_in_progress_ff <= transmission_in_progress_ff(0) & transmission_in_progress;
        end if;
    end process;
    spi_transmission_start <= not transmission_in_progress_ff(1) and transmission_in_progress_ff(0);  -- detect rising edge of transmission_in_progress

    spi_clk <= clk_spi when spi_cs_n = '0' else '0';
    p_dac_spi_output: process(clk_spi, s_reset) is
    begin
        if s_reset = '1' then
            spi_cs_n <= '1';
            spi_data <= '0';
            bit_cnt <= (others => '0');
            spi_transmission_done <= '0';
            spi_busy <= '0';

        elsif rising_edge(clk_spi) then
            spi_data <= '0';
            spi_transmission_done <= '0';
            spi_cs_n <= '1';
            if spi_transmission_start = '1' then
                bit_cnt <= (others => '0');
                shift_reg <= preamble & data_buffer(11 downto 0);
                spi_data <= '0';
                spi_busy <= '1';
                
            elsif spi_transmission_done = '0' and spi_busy='1' then
                spi_data <= shift_reg(15);  -- MSB first
                shift_reg <= shift_reg(14 downto 0) & '0';  -- shift left
                bit_cnt <= bit_cnt + 1;
                spi_cs_n <= '0';  -- active
                
                if bit_cnt = 16 then
                    spi_transmission_done <= '1';
                    bit_cnt <= (others => '0');
                    spi_busy <= '0';
                end if;
            end if;

        end if;
    end process;
end architecture rtl;

quartus_proj_max10/hdl/DAC_SPI/DAC_SPI_tb.vhdl
library ieee;
use ieee.std_logic_1164.all;
use ieee.numeric_std.all;

entity DAC_SPI_tb is
end entity DAC_SPI_tb;

architecture sim of DAC_SPI_tb is

    -- Clock periods
    constant CLK_PERIOD     : time := 5 ns;      -- 200 MHz
    constant SPI_CLK_PERIOD : time := 25 ns;   -- 40 MHz

    signal clk     : std_logic := '0';
    signal clk_spi : std_logic := '0';
    signal rst     : std_logic := '1';

    signal spi_clk  : std_logic;
    signal spi_cs_n : std_logic;
    signal spi_data : std_logic;

    signal asi_data  : std_logic_vector(15 downto 0) := (others => '0');
    signal asi_valid : std_logic := '0';
    signal asi_ready : std_logic;

    -- 2 MHz Avalon data rate -> 500 ns period
    constant AVL_PERIOD : time := 500 ns;

    signal spi_capure_data : std_logic_vector(11 downto 0);
    signal spi_capture_mode : std_logic_vector(3 downto 0);

    signal sim_done : boolean := false;

begin

    -- Clock generators
    clk     <= not clk     after CLK_PERIOD / 2     when not sim_done else '0';
    clk_spi <= not clk_spi after SPI_CLK_PERIOD / 2 when not sim_done else '0';

    -- DUT
    dut : entity work.DAC_SPI
        port map (
            clk      => clk,
            clk_spi  => clk_spi,
            rst      => rst,
            spi_clk  => spi_clk,
            spi_cs_n => spi_cs_n,
            spi_data => spi_data,
            asi_data  => asi_data,
            asi_valid => asi_valid,
            asi_ready => asi_ready
        );

    -- Main stimulus: send 10 values at 2 MHz (500 ns period)
    p_stim : process
        variable t_start : time;
        variable dac_val : std_logic_vector(15 downto 0);
    begin
        rst <= '1';
        asi_valid <= '0';
        asi_data  <= (others => '0');
        wait for 100 ns;
        rst <= '0';
        wait for 100 ns;

        for i in 0 to 9 loop
            t_start := now;
            dac_val := std_logic_vector(to_unsigned((i + 1) * 100, 16));

            -- Wait until DUT is ready, then send value
            wait until rising_edge(clk) and asi_ready = '1';
            asi_data  <= dac_val;
            asi_valid <= '1';
            wait until rising_edge(clk);
            asi_valid <= '0';

            -- Maintain 2 MHz rate: wait remainder of 500 ns period
            if (now - t_start) < AVL_PERIOD then
                wait for AVL_PERIOD - (now - t_start);
            end if;
        end loop;

        -- Wait for last SPI transfer to complete
        wait for 2 us;

        sim_done <= true;
        report "Simulation finished." severity note;
        wait;
    end process;

    -- Simulated DAC slave: capture spi_data on rising edge of spi_clk when CS is low
    p_dac_slave : process
        variable captured : std_logic_vector(15 downto 0);
    begin
        wait until spi_cs_n = '0';
        for bit_idx in 15 downto 0 loop
            wait until falling_edge(spi_clk);
            captured(bit_idx) := spi_data;
        end loop;
        wait until spi_cs_n = '1';
        spi_capure_data <= captured(11 downto 0);
        spi_capture_mode <= captured(15 downto 12);
        -- report "DAC received: 0x" & to_hstring(captured) severity note;
    end process;

end architecture sim;

quartus_proj_max10/hdl/DAC_SPI/func.vcd
$date
  Wed Feb 25 16:56:53 2026
$end
$version
  GHDL v0
$end
$timescale
  1 ns
$end
$scope module standard $end
$upscope $end
$scope module textio $end
$upscope $end
$scope module std_logic_1164 $end
$upscope $end
$scope module numeric_std $end
$upscope $end
$scope module dac_spi_tb $end
$var reg 1 ! clk $end
$var reg 1 " clk_spi $end
$var reg 1 # rst $end
$var reg 1 $ spi_clk $end
$var reg 1 % spi_cs_n $end
$var reg 1 & spi_data $end
$var reg 16 ' asi_data[15:0] $end
$var reg 1 ( asi_valid $end
$var reg 1 ) asi_ready $end
$var reg 12 * spi_capure_data[11:0] $end
$var reg 4 + spi_capture_mode[3:0] $end
$var reg 1 , sim_done $end
$scope module dut $end
$var reg 1 - clk $end
$var reg 1 . clk_spi $end
$var reg 1 / rst $end
$var reg 1 0 spi_clk $end
$var reg 1 1 spi_cs_n $end
$var reg 1 2 spi_data $end
$var reg 16 3 asi_data[15:0] $end
$var reg 1 4 asi_valid $end
$var reg 1 5 asi_ready $end
$var reg 16 6 shift_reg[15:0] $end
$var reg 16 7 data_buffer[15:0] $end
$var reg 5 8 bit_cnt[4:0] $end
$var reg 1 9 s_reset $end
$var reg 1 : spi_transmission_done $end
$var reg 2 ; transmission_in_progress_ff[1:0] $end
$var reg 1 < transmission_in_progress $end
$var reg 1 = spi_busy $end
$var reg 1 > spi_transmission_start $end
$upscope $end
$upscope $end
$enddefinitions $end
#0
0!
0"
1#
0$
1%
0&
b0000000000000000 '
0(
1)
bUUUUUUUUUUUU *
bUUUU +
0,
0-
0.
1/
00
11
02
b0000000000000000 3
04
15
bUUUUUUUUUUUUUUUU 6
b0000000000000000 7
b00000 8
19
0:
b00 ;
0<
0=
0>
#2
1!
1-
#4
0!
0-
#6
1!
1-
#8
0!
0-
#10
1!
1-
#12
0!
1"
0-
1.
#14
1!
1-
#16
0!
0-
#18
1!
1-
#20
0!
0-
#22
1!
1-
#24
0!
0"
0-
0.
#26
1!
1-
#28
0!
0-
#30
1!
1-
#32
0!
0-
#34
1!
1-
#36
0!
1"
0-
1.
#38
1!
1-
#40
0!
0-
#42
1!
1-
#44
0!
0-
#46
1!
1-
#48
0!
0"
0-
0.
#50
1!
1-
#52
0!
0-
#54
1!
1-
#56
0!
0-
#58
1!
1-
#60
0!
1"
0-
1.
#62
1!
1-
#64
0!
0-
#66
1!
1-
#68
0!
0-
#70
1!
1-
#72
0!
0"
0-
0.
#74
1!
1-
#76
0!
0-
#78
1!
1-
#80
0!
0-
#82
1!
1-
#84
0!
1"
0-
1.
#86
1!
1-
#88
0!
0-
#90
1!
1-
#92
0!
0-
#94
1!
1-
#96
0!
0"
0-
0.
#98
1!
1-
#100
0!
0#
0-
0/
09
#102
1!
1-
#104
0!
0-
#106
1!
1-
#108
0!
1"
0-
1.
#110
1!
1-
#112
0!
0-
#114
1!
1-
#116
0!
0-
#118
1!
1-
#120
0!
0"
0-
0.
#122
1!
1-
#124
0!
0-
#126
1!
1-
#128
0!
0-
#130
1!
1-
#132
0!
1"
0-
1.
#134
1!
1-
#136
0!
0-
#138
1!
1-
#140
0!
0-
#142
1!
1-
#144
0!
0"
0-
0.
#146
1!
1-
#148
0!
0-
#150
1!
1-
#152
0!
0-
#154
1!
1-
#156
0!
1"
0-
1.
#158
1!
1-
#160
0!
0-
#162
1!
1-
#164
0!
0-
#166
1!
1-
#168
0!
0"
0-
0.
#170
1!
1-
#172
0!
0-
#174
1!
1-
#176
0!
0-
#178
1!
1-
#180
0!
1"
0-
1.
#182
1!
1-
#184
0!
0-
#186
1!
1-
#188
0!
0-
#190
1!
1-
#192
0!
0"
0-
0.
#194
1!
1-
#196
0!
0-
#198
1!
1-
#200
0!
0-
#202
1!
b0000000001100100 '
1(
1-
b0000000001100100 3
14
#204
0!
1"
0-
1.
#206
1!
0(
0)
1-
04
05
b0000000001100100 7
1<
#208
0!
0-
#210
1!
1-
#212
0!
0-
#214
1!
1-
#216
0!
0"
0-
0.
#218
1!
1-
#220
0!
0-
#222
1!
1-
#224
0!
0-
#226
1!
1-
#228
0!
1"
0-
1.
b01 ;
1>
#230
1!
1-
#232
0!
0-
#234
1!
1-
#236
0!
0-
#238
1!
1-
#240
0!
0"
0-
0.
#242
1!
1-
#244
0!
0-
#246
1!
1-
#248
0!
0-
#250
1!
1-
#252
0!
1"
0-
1.
b0001000001100100 6
b11 ;
1=
0>
#254
1!
1-
#256
0!
0-
#258
1!
1-
#260
0!
0-
#262
1!
1-
#264
0!
0"
0-
0.
#266
1!
1-
#268
0!
0-
#270
1!
1-
#272
0!
0-
#274
1!
1-
#276
0!
1"
1$
0%
0-
1.
10
01
b0010000011001000 6
b00001 8
#278
1!
1-
#280
0!
0-
#282
1!
1-
#284
0!
0-
#286
1!
1-
#288
0!
0"
0$
0-
0.
00
#290
1!
1-
#292
0!
0-
#294
1!
1-
#296
0!
0-
#298
1!
1-
#300
0!
1"
1$
0-
1.
10
01
b0100000110010000 6
b00010 8
#302
1!
1-
#304
0!
0-
#306
1!
1-
#308
0!
0-
#310
1!
1-
#312
0!
0"
0$
0-
0.
00
#314
1!
1-
#316
0!
0-
#318
1!
1-
#320
0!
0-
#322
1!
1-
#324
0!
1"
1$
0-
1.
10
01
b1000001100100000 6
b00011 8
#326
1!
1-
#328
0!
0-
#330
1!
1-
#332
0!
0-
#334
1!
1-
#336
0!
0"
0$
0-
0.
00
#338
1!
1-
#340
0!
0-
#342
1!
1-
#344
0!
0-
#346
1!
1-
#348
0!
1"
1$
1&
0-
1.
10
01
12
b0000011001000000 6
b00100 8
#350
1!
1-
#352
0!
0-
#354
1!
1-
#356
0!
0-
#358
1!
1-
#360
0!
0"
0$
0-
0.
00
#362
1!
1-
#364
0!
0-
#366
1!
1-
#368
0!
0-
#370
1!
1-
#372
0!
1"
1$
0&
0-
1.
10
01
02
b0000110010000000 6
b00101 8
#374
1!
1-
#376
0!
0-
#378
1!
1-
#380
0!
0-
#382
1!
1-
#384
0!
0"
0$
0-
0.
00
#386
1!
1-
#388
0!
0-
#390
1!
1-
#392
0!
0-
#394
1!
1-
#396
0!
1"
1$
0-
1.
10
01
b0001100100000000 6
b00110 8
#398
1!
1-
#400
0!
0-
#402
1!
1-
#404
0!
0-
#406
1!
1-
#408
0!
0"
0$
0-
0.
00
#410
1!
1-
#412
0!
0-
#414
1!
1-
#416
0!
0-
#418
1!
1-
#420
0!
1"
1$
0-
1.
10
01
b0011001000000000 6
b00111 8
#422
1!
1-
#424
0!
0-
#426
1!
1-
#428
0!
0-
#430
1!
1-
#432
0!
0"
0$
0-
0.
00
#434
1!
1-
#436
0!
0-
#438
1!
1-
#440
0!
0-
#442
1!
1-
#444
0!
1"
1$
0-
1.
10
01
b0110010000000000 6
b01000 8
#446
1!
1-
#448
0!
0-
#450
1!
1-
#452
0!
0-
#454
1!
1-
#456
0!
0"
0$
0-
0.
00
#458
1!
1-
#460
0!
0-
#462
1!
1-
#464
0!
0-
#466
1!
1-
#468
0!
1"
1$
0-
1.
10
01
b1100100000000000 6
b01001 8
#470
1!
1-
#472
0!
0-
#474
1!
1-
#476
0!
0-
#478
1!
1-
#480
0!
0"
0$
0-
0.
00
#482
1!
1-
#484
0!
0-
#486
1!
1-
#488
0!
0-
#490
1!
1-
#492
0!
1"
1$
1&
0-
1.
10
01
12
b1001000000000000 6
b01010 8
#494
1!
1-
#496
0!
0-
#498
1!
1-
#500
0!
0-
#502
1!
1-
#504
0!
0"
0$
0-
0.
00
#506
1!
1-
#508
0!
0-
#510
1!
1-
#512
0!
0-
#514
1!
1-
#516
0!
1"
1$
0-
1.
10
01
12
b0010000000000000 6
b01011 8
#518
1!
1-
#520
0!
0-
#522
1!
1-
#524
0!
0-
#526
1!
1-
#528
0!
0"
0$
0-
0.
00
#530
1!
1-
#532
0!
0-
#534
1!
1-
#536
0!
0-
#538
1!
1-
#540
0!
1"
1$
0&
0-
1.
10
01
02
b0100000000000000 6
b01100 8
#542
1!
1-
#544
0!
0-
#546
1!
1-
#548
0!
0-
#550
1!
1-
#552
0!
0"
0$
0-
0.
00
#554
1!
1-
#556
0!
0-
#558
1!
1-
#560
0!
0-
#562
1!
1-
#564
0!
1"
1$
0-
1.
10
01
b1000000000000000 6
b01101 8
#566
1!
1-
#568
0!
0-
#570
1!
1-
#572
0!
0-
#574
1!
1-
#576
0!
0"
0$
0-
0.
00
#578
1!
1-
#580
0!
0-
#582
1!
1-
#584
0!
0-
#586
1!
1-
#588
0!
1"
1$
1&
0-
1.
10
01
12
b0000000000000000 6
b01110 8
#590
1!
1-
#592
0!
0-
#594
1!
1-
#596
0!
0-
#598
1!
1-
#600
0!
0"
0$
0-
0.
00
#602
1!
1-
#604
0!
0-
#606
1!
1-
#608
0!
0-
#610
1!
1-
#612
0!
1"
1$
0&
0-
1.
10
01
02
b01111 8
#614
1!
1-
#616
0!
0-
#618
1!
1-
#620
0!
0-
#622
1!
1-
#624
0!
0"
0$
0-
0.
00
#626
1!
1-
#628
0!
0-
#630
1!
1-
#632
0!
0-
#634
1!
1-
#636
0!
1"
1$
0-
1.
10
01
b10000 8
#638
1!
1-
#640
0!
0-
#642
1!
1-
#644
0!
0-
#646
1!
1-
#648
0!
0"
0$
0-
0.
00
#650
1!
1-
#652
0!
0-
#654
1!
1-
#656
0!
0-
#658
1!
1-
#660
0!
1"
1$
0-
1.
10
01
b00000 8
1:
0=
#662
1!
1)
1-
15
0<
#664
0!
0-
#666
1!
1-
#668
0!
0-
#670
1!
1-
#672
0!
0"
0$
0-
0.
00
#674
1!
1-
#676
0!
0-
#678
1!
1-
#680
0!
0-
#682
1!
1-
#684
0!
1"
0$
1%
b000001100100 *
b0001 +
0-
1.
00
11
0:
b10 ;
#686
1!
1-
#688
0!
0-
#690
1!
1-
#692
0!
0-
#694
1!
1-
#696
0!
0"
0-
0.
#698
1!
1-
#700
0!
0-
#702
1!
b0000000011001000 '
1(
1-
b0000000011001000 3
14
#704
0!
0-
#706
1!
0(
0)
1-
04
05
b0000000011001000 7
1<
#708
0!
1"
0-
1.
b01 ;
1>
#710
1!
1-
#712
0!
0-
#714
1!
1-
#716
0!
0-
#718
1!
1-
#720
0!
0"
0-
0.
#722
1!
1-
#724
0!
0-
#726
1!
1-
#728
0!
0-
#730
1!
1-
#732
0!
1"
0-
1.
b0001000011001000 6
b11 ;
1=
0>
#734
1!
1-
#736
0!
0-
#738
1!
1-
#740
0!
0-
#742
1!
1-
#744
0!
0"
0-
0.
#746
1!
1-
#748
0!
0-
#750
1!
1-
#752
0!
0-
#754
1!
1-
#756
0!
1"
1$
0%
0-
1.
10
01
b0010000110010000 6
b00001 8
#758
1!
1-
#760
0!
0-
#762
1!
1-
#764
0!
0-
#766
1!
1-
#768
0!
0"
0$
0-
0.
00
#770
1!
1-
#772
0!
0-
#774
1!
1-
#776
0!
0-
#778
1!
1-
#780
0!
1"
1$
0-
1.
10
01
b0100001100100000 6
b00010 8
#782
1!
1-
#784
0!
0-
#786
1!
1-
#788
0!
0-
#790
1!
1-
#792
0!
0"
0$
0-
0.
00
#794
1!
1-
#796
0!
0-
#798
1!
1-
#800
0!
0-
#802
1!
1-
#804
0!
1"
1$
0-
1.
10
01
b1000011001000000 6
b00011 8
#806
1!
1-
#808
0!
0-
#810
1!
1-
#812
0!
0-
#814
1!
1-
#816
0!
0"
0$
0-
0.
00
#818
1!
1-
#820
0!
0-
#822
1!
1-
#824
0!
0-
#826
1!
1-
#828
0!
1"
1$
1&
0-
1.
10
01
12
b0000110010000000 6
b00100 8
#830
1!
1-
#832
0!
0-
#834
1!
1-
#836
0!
0-
#838
1!
1-
#840
0!
0"
0$
0-
0.
00
#842
1!
1-
#844
0!
0-
#846
1!
1-
#848
0!
0-
#850
1!
1-
#852
0!
1"
1$
0&
0-
1.
10
01
02
b0001100100000000 6
b00101 8
#854
1!
1-
#856
0!
0-
#858
1!
1-
#860
0!
0-
#862
1!
1-
#864
0!
0"
0$
0-
0.
00
#866
1!
1-
#868
0!
0-
#870
1!
1-
#872
0!
0-
#874
1!
1-
#876
0!
1"
1$
0-
1.
10
01
b0011001000000000 6
b00110 8
#878
1!
1-
#880
0!
0-
#882
1!
1-
#884
0!
0-
#886
1!
1-
#888
0!
0"
0$
0-
0.
00
#890
1!
1-
#892
0!
0-
#894
1!
1-
#896
0!
0-
#898
1!
1-
#900
0!
1"
1$
0-
1.
10
01
b0110010000000000 6
b00111 8
#902
1!
1-
#904
0!
0-
#906
1!
1-
#908
0!
0-
#910
1!
1-
#912
0!
0"
0$
0-
0.
00
#914
1!
1-
#916
0!
0-
#918
1!
1-
#920
0!
0-
#922
1!
1-
#924
0!
1"
1$
0-
1.
10
01
b1100100000000000 6
b01000 8
#926
1!
1-
#928
0!
0-
#930
1!
1-
#932
0!
0-
#934
1!
1-
#936
0!
0"
0$
0-
0.
00
#938
1!
1-
#940
0!
0-
#942
1!
1-
#944
0!
0-
#946
1!
1-
#948
0!
1"
1$
1&
0-
1.
10
01
12
b1001000000000000 6
b01001 8
#950
1!
1-
#952
0!
0-
#954
1!
1-
#956
0!
0-
#958
1!
1-
#960
0!
0"
0$
0-
0.
00
#962
1!
1-
#964
0!
0-
#966
1!
1-
#968
0!
0-
#970
1!
1-
#972
0!
1"
1$
0-
1.
10
01
12
b0010000000000000 6
b01010 8
#974
1!
1-
#976
0!
0-
#978
1!
1-
#980
0!
0-
#982
1!
1-
#984
0!
0"
0$
0-
0.
00
#986
1!
1-
#988
0!
0-
#990
1!
1-
#992
0!
0-
#994
1!
1-
#996
0!
1"
1$
0&
0-
1.
10
01
02
b0100000000000000 6
b01011 8
#998
1!
1-
#1000
0!
0-
#1002
1!
1-
#1004
0!
0-
#1006
1!
1-
#1008
0!
0"
0$
0-
0.
00
#1010
1!
1-
#1012
0!
0-
#1014
1!
1-
#1016
0!
0-
#1018
1!
1-
#1020
0!
1"
1$
0-
1.
10
01
b1000000000000000 6
b01100 8
#1022
1!
1-
#1024
0!
0-
#1026
1!
1-
#1028
0!
0-
#1030
1!
1-
#1032
0!
0"
0$
0-
0.
00
#1034
1!
1-
#1036
0!
0-
#1038
1!
1-
#1040
0!
0-
#1042
1!
1-
#1044
0!
1"
1$
1&
0-
1.
10
01
12
b0000000000000000 6
b01101 8
#1046
1!
1-
#1048
0!
0-
#1050
1!
1-
#1052
0!
0-
#1054
1!
1-
#1056
0!
0"
0$
0-
0.
00
#1058
1!
1-
#1060
0!
0-
#1062
1!
1-
#1064
0!
0-
#1066
1!
1-
#1068
0!
1"
1$
0&
0-
1.
10
01
02
b01110 8
#1070
1!
1-
#1072
0!
0-
#1074
1!
1-
#1076
0!
0-
#1078
1!
1-
#1080
0!
0"
0$
0-
0.
00
#1082
1!
1-
#1084
0!
0-
#1086
1!
1-
#1088
0!
0-
#1090
1!
1-
#1092
0!
1"
1$
0-
1.
10
01
b01111 8
#1094
1!
1-
#1096
0!
0-
#1098
1!
1-
#1100
0!
0-
#1102
1!
1-
#1104
0!
0"
0$
0-
0.
00
#1106
1!
1-
#1108
0!
0-
#1110
1!
1-
#1112
0!
0-
#1114
1!
1-
#1116
0!
1"
1$
0-
1.
10
01
b10000 8
#1118
1!
1-
#1120
0!
0-
#1122
1!
1-
#1124
0!
0-
#1126
1!
1-
#1128
0!
0"
0$
0-
0.
00
#1130
1!
1-
#1132
0!
0-
#1134
1!
1-
#1136
0!
0-
#1138
1!
1-
#1140
0!
1"
1$
0-
1.
10
01
b00000 8
1:
0=
#1142
1!
1)
1-
15
0<
#1144
0!
0-
#1146
1!
1-
#1148
0!
0-
#1150
1!
1-
#1152
0!
0"
0$
0-
0.
00
#1154
1!
1-
#1156
0!
0-
#1158
1!
1-
#1160
0!
0-
#1162
1!
1-
#1164
0!
1"
0$
1%
b000011001000 *
0-
1.
00
11
0:
b10 ;
#1166
1!
1-
#1168
0!
0-
#1170
1!
1-
#1172
0!
0-
#1174
1!
1-
#1176
0!
0"
0-
0.
#1178
1!
1-
#1180
0!
0-
#1182
1!
1-
#1184
0!
0-
#1186
1!
1-
#1188
0!
1"
0-
1.
b00 ;
#1190
1!
1-
#1192
0!
0-
#1194
1!
1-
#1196
0!
0-
#1198
1!
1-
#1200
0!
0"
0-
0.
#1202
1!
b0000000100101100 '
1(
1-
b0000000100101100 3
14
#1204
0!
0-
#1206
1!
0(
0)
1-
04
05
b0000000100101100 7
1<
#1208
0!
0-
#1210
1!
1-
#1212
0!
1"
0-
1.
b01 ;
1>
#1214
1!
1-
#1216
0!
0-
#1218
1!
1-
#1220
0!
0-
#1222
1!
1-
#1224
0!
0"
0-
0.
#1226
1!
1-
#1228
0!
0-
#1230
1!
1-
#1232
0!
0-
#1234
1!
1-
#1236
0!
1"
0-
1.
b0001000100101100 6
b11 ;
1=
0>
#1238
1!
1-
#1240
0!
0-
#1242
1!
1-
#1244
0!
0-
#1246
1!
1-
#1248
0!
0"
0-
0.
#1250
1!
1-
#1252
0!
0-
#1254
1!
1-
#1256
0!
0-
#1258
1!
1-
#1260
0!
1"
1$
0%
0-
1.
10
01
b0010001001011000 6
b00001 8
#1262
1!
1-
#1264
0!
0-
#1266
1!
1-
#1268
0!
0-
#1270
1!
1-
#1272
0!
0"
0$
0-
0.
00
#1274
1!
1-
#1276
0!
0-
#1278
1!
1-
#1280
0!
0-
#1282
1!
1-
#1284
0!
1"
1$
0-
1.
10
01
b0100010010110000 6
b00010 8
#1286
1!
1-
#1288
0!
0-
#1290
1!
1-
#1292
0!
0-
#1294
1!
1-
#1296
0!
0"
0$
0-
0.
00
#1298
1!
1-
#1300
0!
0-
#1302
1!
1-
#1304
0!
0-
#1306
1!
1-
#1308
0!
1"
1$
0-
1.
10
01
b1000100101100000 6
b00011 8
#1310
1!
1-
#1312
0!
0-
#1314
1!
1-
#1316
0!
0-
#1318
1!
1-
#1320
0!
0"
0$
0-
0.
00
#1322
1!
1-
#1324
0!
0-
#1326
1!
1-
#1328
0!
0-
#1330
1!
1-
#1332
0!
1"
1$
1&
0-
1.
10
01
12
b0001001011000000 6
b00100 8
#1334
1!
1-
#1336
0!
0-
#1338
1!
1-
#1340
0!
0-
#1342
1!
1-
#1344
0!
0"
0$
0-
0.
00
#1346
1!
1-
#1348
0!
0-
#1350
1!
1-
#1352
0!
0-
#1354
1!
1-
#1356
0!
1"
1$
0&
0-
1.
10
01
02
b0010010110000000 6
b00101 8
#1358
1!
1-
#1360
0!
0-
#1362
1!
1-
#1364
0!
0-
#1366
1!
1-
#1368
0!
0"
0$
0-
0.
00
#1370
1!
1-
#1372
0!
0-
#1374
1!
1-
#1376
0!
0-
#1378
1!
1-
#1380
0!
1"
1$
0-
1.
10
01
b0100101100000000 6
b00110 8
#1382
1!
1-
#1384
0!
0-
#1386
1!
1-
#1388
0!
0-
#1390
1!
1-
#1392
0!
0"
0$
0-
0.
00
#1394
1!
1-
#1396
0!
0-
#1398
1!
1-
#1400
0!
0-
#1402
1!
1-
#1404
0!
1"
1$
0-
1.
10
01
b1001011000000000 6
b00111 8
#1406
1!
1-
#1408
0!
0-
#1410
1!
1-
#1412
0!
0-
#1414
1!
1-
#1416
0!
0"
0$
0-
0.
00
#1418
1!
1-
#1420
0!
0-
#1422
1!
1-
#1424
0!
0-
#1426
1!
1-
#1428
0!
1"
1$
1&
0-
1.
10
01
12
b0010110000000000 6
b01000 8
#1430
1!
1-
#1432
0!
0-
#1434
1!
1-
#1436
0!
0-
#1438
1!
1-
#1440
0!
0"
0$
0-
0.
00
#1442
1!
1-
#1444
0!
0-
#1446
1!
1-
#1448
0!
0-
#1450
1!
1-
#1452
0!
1"
1$
0&
0-
1.
10
01
02
b0101100000000000 6
b01001 8
#1454
1!
1-
#1456
0!
0-
#1458
1!
1-
#1460
0!
0-
#1462
1!
1-
#1464
0!
0"
0$
0-
0.
00
#1466
1!
1-
#1468
0!
0-
#1470
1!
1-
#1472
0!
0-
#1474
1!
1-
#1476
0!
1"
1$
0-
1.
10
01
b1011000000000000 6
b01010 8
#1478
1!
1-
#1480
0!
0-
#1482
1!
1-
#1484
0!
0-
#1486
1!
1-
#1488
0!
0"
0$
0-
0.
00
#1490
1!
1-
#1492
0!
0-
#1494
1!
1-
#1496
0!
0-
#1498
1!
1-
#1500
0!
1"
1$
1&
0-
1.
10
01
12
b0110000000000000 6
b01011 8
#1502
1!
1-
#1504
0!
0-
#1506
1!
1-
#1508
0!
0-
#1510
1!
1-
#1512
0!
0"
0$
0-
0.
00
#1514
1!
1-
#1516
0!
0-
#1518
1!
1-
#1520
0!
0-
#1522
1!
1-
#1524
0!
1"
1$
0&
0-
1.
10
01
02
b1100000000000000 6
b01100 8
#1526
1!
1-
#1528
0!
0-
#1530
1!
1-
#1532
0!
0-
#1534
1!
1-
#1536
0!
0"
0$
0-
0.
00
#1538
1!
1-
#1540
0!
0-
#1542
1!
1-
#1544
0!
0-
#1546
1!
1-
#1548
0!
1"
1$
1&
0-
1.
10
01
12
b1000000000000000 6
b01101 8
#1550
1!
1-
#1552
0!
0-
#1554
1!
1-
#1556
0!
0-
#1558
1!
1-
#1560
0!
0"
0$
0-
0.
00
#1562
1!
1-
#1564
0!
0-
#1566
1!
1-
#1568
0!
0-
#1570
1!
1-
#1572
0!
1"
1$
0-
1.
10
01
12
b0000000000000000 6
b01110 8
#1574
1!
1-
#1576
0!
0-
#1578
1!
1-
#1580
0!
0-
#1582
1!
1-
#1584
0!
0"
0$
0-
0.
00
#1586
1!
1-
#1588
0!
0-
#1590
1!
1-
#1592
0!
0-
#1594
1!
1-
#1596
0!
1"
1$
0&
0-
1.
10
01
02
b01111 8
#1598
1!
1-
#1600
0!
0-
#1602
1!
1-
#1604
0!
0-
#1606
1!
1-
#1608
0!
0"
0$
0-
0.
00
#1610
1!
1-
#1612
0!
0-
#1614
1!
1-
#1616
0!
0-
#1618
1!
1-
#1620
0!
1"
1$
0-
1.
10
01
b10000 8
#1622
1!
1-
#1624
0!
0-
#1626
1!
1-
#1628
0!
0-
#1630
1!
1-
#1632
0!
0"
0$
0-
0.
00
#1634
1!
1-
#1636
0!
0-
#1638
1!
1-
#1640
0!
0-
#1642
1!
1-
#1644
0!
1"
1$
0-
1.
10
01
b00000 8
1:
0=
#1646
1!
1)
1-
15
0<
#1648
0!
0-
#1650
1!
1-
#1652
0!
0-
#1654
1!
1-
#1656
0!
0"
0$
0-
0.
00
#1658
1!
1-
#1660
0!
0-
#1662
1!
1-
#1664
0!
0-
#1666
1!
1-
#1668
0!
1"
0$
1%
b000100101100 *
0-
1.
00
11
0:
b10 ;
#1670
1!
1-
#1672
0!
0-
#1674
1!
1-
#1676
0!
0-
#1678
1!
1-
#1680
0!
0"
0-
0.
#1682
1!
1-
#1684
0!
0-
#1686
1!
1-
#1688
0!
0-
#1690
1!
1-
#1692
0!
1"
0-
1.
b00 ;
#1694
1!
1-
#1696
0!
0-
#1698
1!
1-
#1700
0!
0-
#1702
1!
b0000000110010000 '
1(
1-
b0000000110010000 3
14
#1704
0!
0"
0-
0.
#1706
1!
0(
0)
1-
04
05
b0000000110010000 7
1<
#1708
0!
0-
#1710
1!
1-
#1712
0!
0-
#1714
1!
1-
#1716
0!
1"
0-
1.
b01 ;
1>
#1718
1!
1-
#1720
0!
0-
#1722
1!
1-
#1724
0!
0-
#1726
1!
1-
#1728
0!
0"
0-
0.
#1730
1!
1-
#1732
0!
0-
#1734
1!
1-
#1736
0!
0-
#1738
1!
1-
#1740
0!
1"
0-
1.
b0001000110010000 6
b11 ;
1=
0>
#1742
1!
1-
#1744
0!
0-
#1746
1!
1-
#1748
0!
0-
#1750
1!
1-
#1752
0!
0"
0-
0.
#1754
1!
1-
#1756
0!
0-
#1758
1!
1-
#1760
0!
0-
#1762
1!
1-
